musicpackbuilder/__init__.py
musicpackbuilder/cli.py
musicpackbuilder/data/en_au.json
musicpackbuilder/data/en_us.json
musicpackbuilder/data/pack.mcmeta
musicpackbuilder/data/pack.png
musicpackbuilder-2.0.0.dist-info/METADATA
musicpackbuilder-2.0.0.dist-info/WHEEL
musicpackbuilder-2.0.0.dist-info/entry_points.txt
musicpackbuilder-2.0.0.dist-info/top_level.txt
musicpackbuilder-2.0.0.dist-info/RECORD
