Metadata-Version: 2.4
Name: musicpackbuilder
Version: 2.0.0
Summary: Create Minecraft music disc resource packs from audio files.
Author: Lochana
Requires-Python: >=3.9
Requires-Dist: mutagen
Requires-Dist: pydub
